mjdippkg/__init__.py
mjdippkg/comparession.py
mjdippkg/extendedSegmentation.py
mjdippkg/featureExtractor.py
mjdippkg/filter.py
mjdippkg/frequencyFilter.py
mjdippkg/histogram.py
mjdippkg/noise.py
mjdippkg/pointProcessing.py
mjdippkg/segmentation.py
mjdippkg/shapeAnalysis.py
mjdippkg/superResolution.py
mjdippkg/textureAnalyzer.py
mjdippkg-0.1.0.dist-info/METADATA
mjdippkg-0.1.0.dist-info/WHEEL
mjdippkg-0.1.0.dist-info/RECORD
